[1,["4eSpHGIaVLBqiygoYA2rVv","53hlyP0KdDKochx6FMjzJu","01kwibQBVAbZQJBgY2RLBt","9cBT9QFAZLpbiPuIf5rTMR","afwbKg+ZtMf5kD1q55nQHZ","9cZ79Tc+VKVKk3vVsm9C9U","2bcQAyUv1Hq4V0kjEOqpNU","98z61ownxFrJX0UAaoCK7L","37bRWq+OJHMbLdpbz3ebW7","e16u1nSu9KNqh3GRYSKJPL","a3NBJEx+pJBYuqB5O6+adO","e9fgYuQalNeawiaB7YYMlk","ddPmC58BZI/4wNnsHf0c8X","94sizEABVC75OXJs4k40Xt","4cnC+1P/pKrZk9VbSeTLpg","d1QhgmmIlNHrsOOBS+Y81i","91aZjBb/RDwrJTs1QyBaOt","56hIaIMPdDVKdXHGFjceIs"],["_textureSetter","dibiao","jinjing_1","jinjing_2","jinjing_3","jinjing_4","jinjing_5","jinjing_6","yuanjing_1","yuanjing_2","yuanjing_3","yun","zhongjing_1","zhongjing_2","zhongjing_3","zhongjing_4","zhongjing_5","zhongjing_dibiao"],["cc.SpriteFrame",["cc.SpriteAtlas",["_name","_spriteFrames"],2,11]],[[1,0,1,2]],[[[{"name":"jinjing_1","rect":[726,244,138,158],"offset":[0,0],"originalSize":[138,158],"capInsets":[0,0,0,0]}],[0],0,[0],[0],[0]],[[{"name":"jinjing_5","rect":[486,0,94,89],"offset":[0,0],"originalSize":[94,89],"capInsets":[0,0,0,0]}],[0],0,[0],[0],[0]],[[{"name":"yuanjing_1","rect":[0,402,145,168],"offset":[0,0],"originalSize":[145,168],"capInsets":[0,0,0,0]}],[0],0,[0],[0],[0]],[[{"name":"zhongjing_3","rect":[0,0,141,45],"offset":[0,0],"originalSize":[141,45],"capInsets":[0,0,0,0]}],[0],0,[0],[0],[0]],[[{"name":"dibiao","rect":[271,402,720,364],"offset":[0,0],"originalSize":[720,364],"capInsets":[0,0,0,0]}],[0],0,[0],[0],[0]],[[{"name":"zhongjing_dibiao","rect":[0,244,726,146],"offset":[0,0],"originalSize":[726,146],"capInsets":[0,0,0,0]}],[0],0,[0],[0],[0]],[[[0,"BgMap2.plist",[{},"dibiao",6,0,"jinjing_1",6,1,"jinjing_2",6,2,"jinjing_3",6,3,"jinjing_4",6,4,"jinjing_5",6,5,"jinjing_6",6,6,"yuanjing_1",6,7,"yuanjing_2",6,8,"yuanjing_3",6,9,"yun",6,10,"zhongjing_1",6,11,"zhongjing_2",6,12,"zhongjing_3",6,13,"zhongjing_4",6,14,"zhongjing_5",6,15,"zhongjing_dibiao",6,16]]],0,0,[0,0,0,0,0,0,0,0,0,0,0,0,0,0,0,0,0],[1,2,3,4,5,6,7,8,9,10,11,12,13,14,15,16,17],[1,2,3,4,5,6,7,8,9,10,11,12,13,14,15,16,17]],[[{"name":"zhongjing_5","rect":[305,0,116,71],"offset":[0,0],"originalSize":[116,71],"capInsets":[0,0,0,0]}],[0],0,[0],[0],[0]],[[{"name":"zhongjing_2","rect":[176,106,145,113],"offset":[0,0],"originalSize":[145,113],"capInsets":[0,0,0,0]}],[0],0,[0],[0],[0]],[[{"name":"jinjing_6","rect":[145,402,126,207],"offset":[0,0],"originalSize":[126,207],"capInsets":[0,0,0,0]}],[0],0,[0],[0],[0]],[[{"name":"jinjing_2","rect":[399,106,118,132],"offset":[0,0],"originalSize":[118,132],"capInsets":[0,0,0,0]}],[0],0,[0],[0],[0]],[[{"name":"jinjing_4","rect":[141,0,164,67],"offset":[0,0],"originalSize":[164,67],"capInsets":[0,0,0,0]}],[0],0,[0],[0],[0]],[[{"name":"yuanjing_3","rect":[0,106,176,109],"offset":[0,0],"originalSize":[176,109],"capInsets":[0,0,0,0]}],[0],0,[0],[0],[0]],[[{"name":"jinjing_3","rect":[517,106,201,132],"offset":[0,0],"originalSize":[201,132],"capInsets":[0,0,0,0]}],[0],0,[0],[0],[0]],[[{"name":"zhongjing_4","rect":[718,106,101,138],"offset":[0,0],"originalSize":[101,138],"capInsets":[0,0,0,0]}],[0],0,[0],[0],[0]],[[{"name":"zhongjing_1","rect":[321,106,78,122],"offset":[0,0],"originalSize":[78,122],"capInsets":[0,0,0,0]}],[0],0,[0],[0],[0]],[[{"name":"yuanjing_2","rect":[421,0,65,85],"offset":[0,0],"originalSize":[65,85],"capInsets":[0,0,0,0]}],[0],0,[0],[0],[0]],[[{"name":"yun","rect":[580,0,287,106],"offset":[0,0],"originalSize":[287,106],"capInsets":[0,0,0,0]}],[0],0,[0],[0],[0]]]]