[1,["1a2j8KpOxFspX0u+MoX8lm","33aEBuBshFT5MoXXdFuovb"],["_textureSetter","value"],["cc.SpriteFrame",["cc.AnimationClip",["_name","_duration","sample","wrapMode","curveData"],-1,11]],[[1,0,1,2,3,4,5]],[[[{"name":"wfg_00","rect":[0,0,84,97],"offset":[0,0],"originalSize":[84,97],"capInsets":[0,0,0,0]}],[0],0,[0],[0],[0]],[[[0,"lantern",2.5,12,2,[{"props":{"opacity":[{"frame":0,"value":150},{"frame":1.25,"value":255},{"frame":2.5,"value":150}]}},"comps",11,[{},"cc.Sprite",11,[{},"spriteFrame",12,[[[{"frame":0},"value",6,0]],11]]]]]],0,0,[0],[1],[1]]]]